py_xrd_visualize/XYs.py
py_xrd_visualize/__init__.py
py_xrd_visualize/optimize.py
py_xrd_visualize/py.typed
py_xrd_visualize/user.py
py_xrd_visualize/visualize.py
py_xrd_visualize/xrd.py
py_xrd_visualize-0.2.1.dist-info/METADATA
py_xrd_visualize-0.2.1.dist-info/WHEEL
py_xrd_visualize-0.2.1.dist-info/licenses/LICENSE
py_xrd_visualize-0.2.1.dist-info/RECORD
